{"body_part": "skirt suit", "visible_part": "complete", "species": "women", "fabric": "wool spinning", "placket": "hedging", "season": "summer", "pocket": "no pocket", "type_version": "fit", "texture": "geometric pattern", "skirt_length": "long skirt", "cloth_orientation": "back", "waist": "none", "suitable_age": "middle age (35-49)", "category": "dress", "hem": "conventional", "upper_dress_contour": "H type", "collar": "round neck", "sleeve_type": "regular sleeve", "coat_length": "none", "sleeve_length": "long sleeve", "elbow": "conventional", "suit": "pants suit", "pant_length": "none", "pants_contour": "none", "craft": "printing", "style": "casual_Western style_Korean version", "accessories": "No accessories", "pattern": "no pattern"}
